sphinxcontrib_shellcheck-1.1.2-py3.6-nspkg.pth
sphinxcontrib/shellcheck.py
sphinxcontrib_shellcheck-1.1.2.dist-info/AUTHORS.rst
sphinxcontrib_shellcheck-1.1.2.dist-info/LICENSE
sphinxcontrib_shellcheck-1.1.2.dist-info/METADATA
sphinxcontrib_shellcheck-1.1.2.dist-info/WHEEL
sphinxcontrib_shellcheck-1.1.2.dist-info/namespace_packages.txt
sphinxcontrib_shellcheck-1.1.2.dist-info/top_level.txt
sphinxcontrib_shellcheck-1.1.2.dist-info/RECORD
