Metadata-Version: 2.1
Name: sphinxcontrib-shellcheck
Version: 1.1.2
Summary: Sphinx extension to lint shell code blocks
Home-page: https://github.com/pmacosta/sphinxcontrib-shellcheck
Author: Pablo Acosta-Serafini
Author-email: pmasdev@gmail.com
License: MIT
Platform: any
Classifier: Programming Language :: Python :: 3.5
Classifier: Programming Language :: Python :: 3.6
Classifier: Programming Language :: Python :: 3.7
Classifier: Programming Language :: Python :: 3.8
Classifier: Development Status :: 5 - Production/Stable
Classifier: Natural Language :: English
Classifier: Environment :: Console
Classifier: Intended Audience :: Developers
Classifier: License :: OSI Approved :: MIT License
Classifier: Operating System :: OS Independent
Classifier: Framework :: Sphinx :: Extension
Classifier: Topic :: Software Development :: Documentation
